arcane/spreadsheet/__init__.py
arcane/spreadsheet/sp_duplicator_cf_utils.py
arcane/spreadsheet/spreadsheet.py
arcane_spreadsheet-0.6.2.dist-info/METADATA
arcane_spreadsheet-0.6.2.dist-info/WHEEL
arcane_spreadsheet-0.6.2.dist-info/RECORD
