Metadata-Version: 2.4
Name: arcane-spreadsheet
Version: 0.6.2
Summary: Arcane spreadsheet tools
Author: Arcane
Author-email: product@wearcane.com
Requires-Python: >=3.6,<4.0
Classifier: Programming Language :: Python :: 3
Classifier: Programming Language :: Python :: 3.6
Classifier: Programming Language :: Python :: 3.7
Classifier: Programming Language :: Python :: 3.8
Classifier: Programming Language :: Python :: 3.9
Classifier: Programming Language :: Python :: 3.10
Classifier: Programming Language :: Python :: 3.11
Classifier: Programming Language :: Python :: 3.12
Classifier: Programming Language :: Python :: 3.13
Classifier: Programming Language :: Python :: 3.14
Requires-Dist: arcane-core (>=1.6.0,<2.0.0)
Requires-Dist: arcane-requests (>=0.0.0,<1.0.0)
Requires-Dist: google-api-python-client (>=2.40.0,<3.0.0)
Requires-Dist: oauth2client (==4.1.3)
